kor/__init__.py
kor/errors.py
kor/kor_file.py
kor/value_type.py
kor_project-0.2.1.dist-info/LICENSE
kor_project-0.2.1.dist-info/METADATA
kor_project-0.2.1.dist-info/WHEEL
kor_project-0.2.1.dist-info/top_level.txt
kor_project-0.2.1.dist-info/RECORD
