Metadata-Version: 2.1
Name: kor-project
Version: 0.2.1
Summary: Use this package to work with kor files
Home-page: https://github.com/KoraKu/Kor_Project
Author: Hugo Costa
Author-email: costhug@orange.fr
License: UNKNOWN
Platform: UNKNOWN
Classifier: Programming Language :: Python :: 3
Classifier: Programming Language :: Python :: 3.7
Classifier: Operating System :: OS Independent
Classifier: License :: OSI Approved :: MIT License
